setup.py
c2sun_distributions/Binomialdistribution.py
c2sun_distributions/Gaussiandistribution.py
c2sun_distributions/Generaldistribution.py
c2sun_distributions/__init__.py
c2sun_distributions.egg-info/PKG-INFO
c2sun_distributions.egg-info/SOURCES.txt
c2sun_distributions.egg-info/dependency_links.txt
c2sun_distributions.egg-info/not-zip-safe
c2sun_distributions.egg-info/top_level.txt