Metadata-Version: 1.0
Name: c2sun-distributions
Version: 0.1
Summary: Gaussian and Binomial distributions
Home-page: UNKNOWN
Author: Chenggui Sun
Author-email: cgsun0521@hotmail.com
License: UNKNOWN
Platform: UNKNOWN
